{
  "schemaVersion": 1,
  "id": "feldsparmod",
  "version": "${version}",

  "name": "Feldspar Mod",
  "description": "Useless Mod",
  "authors": [
    "Feldspar!"
  ],
  "contact": {
    "homepage": "https://fabricmc.net/",
    "sources": "https://github.com/2002luis/crappyMinecraftMod"
  },

  "license": "MIT",
  "icon": "assets/modid/icon.png",

  "environment": "*",
  "entrypoints": {
    "main": [
      "net.feldspar.feldsparmod.FeldsparMod"
    ]
  },
  "mixins": [
    "feldsparmod.mixins.json"
  ],

  "depends": {
    "fabricloader": ">=0.13.3",
    "fabric": "*",
    "minecraft": "1.18.x",
    "java": ">=17"
  },
  "suggests": {
    "another-mod": "*"
  }
}
